<?xml version="1.0" encoding="utf-8"?>
<tv xmlns:xsi="http://www.w3.org/2001/XMLSchema-instance" xmlns:xsd="http://www.w3.org/2001/XMLSchema">
  <programme channel="test" start="20151124060500 +0100" stop="20151124070000 +0100" originid="" reserve="no">
    <date>2015-11-26</date>
    <title>De parfaits coupables</title>
    <subTitle />
    <desc>En 2003, Abdelkader Azzimani et Brahim El Jabri, deux Marocains qui clament leur innocence, sont condamnés à vingt ans de réclusion pour homicide... (Lire la suite).(n)</desc>
  </programme>
  <programme channel="test" start="20151124070000 +0100" stop="20151124083000 +0100" originid="" reserve="no">
    <date>2015-11-26</date>
    <title>La folie des régimes</title>
    <subTitle />
    <desc>Liza Fanjeaux a enquêté sur les dessous du business des régimes et des méthodes d'amaigrissement. Ce secteur florissant a profondément modifié... (Lire la suite).(n)</desc>
  </programme>
  <programme channel="test" start="20151124083000 +0100" stop="20151124090000 +0100" originid="" reserve="no">
    <date>2015-11-26</date>
    <title>Interruption des programmes</title>
    <subTitle />
    <desc>(Lire la suite).(n)</desc>
  </programme>
  <programme channel="test" start="20151124090000 +0100" stop="20151124092500 +0100" originid="" reserve="no">
    <date>2015-11-26</date>
    <title>L'oeil de Links</title>
    <subTitle />
    <desc>Le webazine de l'activité créative du net : webséries, collaborations diverses, créations de contenus, innovations ingénieuses, rien n'échappe à... (Lire la suite).(n)</desc>
  </programme>
  <programme channel="test" start="20151124092500 +0100" stop="20151124102500 +0100" originid="" reserve="no">
    <date>2015-11-26</date>
    <title>Attrape-moi si tu peux !</title>
    <subTitle />
    <desc>FN / UMP : la surenchère A la veille des municipales, la droite tremble : comment les candidats UMP peuvent-ils résister à la poussée du Front national ? Pour comprendre... (Lire la suite).(n)</desc>
  </programme>
  <programme channel="test" start="20151124102500 +0100" stop="20151124121000 +0100" originid="" reserve="no">
    <date>2015-11-26</date>
    <title>The Gambler (?)</title>
    <subTitle />
    <desc>Jim Bennett aurait tout pour mener sa vie d'enseignant avec passion s'il n'était dévoré par le démon du jeu. Totalement possédé, il doit des... (Lire la suite).(n)</desc>
  </programme>
  <programme channel="test" start="20151124121000 +0100" stop="20151124123000 +0100" originid="" reserve="no">
    <date>2015-11-26</date>
    <title>Anger Management</title>
    <subTitle>Charlie et la petite curieuse</subTitle>
    <desc>Charlie devient paranoïaque lorsqu'il découvre, avec surprise, qu'il sort avec une détective privée. Lacey rejoint Nolan et emménage dans sa... (Lire la suite).(n)</desc>
  </programme>
  <programme channel="test" start="20151124123000 +0100" stop="20151124125500 +0100" originid="" reserve="no">
    <date>2015-11-26</date>
    <title>Anger Management</title>
    <subTitle>Soeurs ennemies</subTitle>
    <desc>Charlie tombe tête baissée dans le piège astucieusement tendu par Jordan. Celui-ci l'autorise à lui arranger un rendez-vous avec une fille, sa... (Lire la suite).(n)</desc>
  </programme>
  <programme channel="test" start="20151124125500 +0100" stop="20151124131500 +0100" originid="" reserve="no">
    <date>2015-11-26</date>
    <title>Parks and Recreation</title>
    <subTitle>Jumelage</subTitle>
    <desc>Leslie accueille une délégation venue tout droit de la ville jumelée à Pawnee au Venezuela, Boraqua. Immédiatement, certaines différences... (Lire la suite).(n)</desc>
  </programme>
  <programme channel="test" start="20151124131500 +0100" stop="20151124133500 +0100" originid="" reserve="no">
    <date>2015-11-26</date>
    <title>Parks and Recreation</title>
    <subTitle>Parc Express</subTitle>
    <desc>Leslie et quelques autres volontaires du comité apportent leur aide à une organisation locale qui souhaite construire une petite aire de jeux,... (Lire la suite).(n)</desc>
  </programme>
  <programme channel="test" start="20151124133500 +0100" stop="20151124140000 +0100" originid="" reserve="no">
    <date>2015-11-26</date>
    <title>Album de la semaine</title>
    <subTitle />
    <desc>Faada Freddy Couvrant des genres aussi variés que la soul, le gospel, le hip-hop, l'indie rock, la musique afro-américaine et le beatboxing, Faada Freddy a su... (Lire la suite).(n)</desc>
  </programme>
  <programme channel="test" start="20151124140000 +0100" stop="20151124160500 +0100" originid="" reserve="no">
    <date>2015-11-26</date>
    <title>Her (?)</title>
    <subTitle />
    <desc>Dans un futur proche à Los Angeles, Theodore Twombly tente de se remettre de sa rupture avec Catherine, qui lui a brisé le coeur. Théodore est un... (Lire la suite).(n)</desc>
  </programme>
  <programme channel="test" start="20151124160500 +0100" stop="20151124170000 +0100" originid="" reserve="no">
    <date>2015-11-26</date>
    <title>Happy Valley</title>
    <subTitle />
    <desc>Après la visite de Catherine, Royce décide de trouver un autre refuge pour Ann. Sur le chemin, il évite une arrestation en percutant violemment... (Lire la suite).(n)</desc>
  </programme>
  <programme channel="test" start="20151124170000 +0100" stop="20151124180000 +0100" originid="" reserve="no">
    <date>2015-11-26</date>
    <title>Happy Valley</title>
    <subTitle />
    <desc>Hantée par la mort de Kirsten, Catherine se laisse submerger par la mélancolie et perd l'envie de retrouver Royce. Elle obtient toutefois un... (Lire la suite).(n)</desc>
  </programme>
  <programme channel="test" start="20151124180000 +0100" stop="20151124183000 +0100" originid="" reserve="no">
    <date>2015-11-26</date>
    <title>L'oeil de Links</title>
    <subTitle />
    <desc>Le webazine de l'activité créative du net : webséries, collaborations diverses, créations de contenus, innovations ingénieuses, rien n'échappe à... (Lire la suite).(n)</desc>
  </programme>
  <programme channel="test" start="20151124183000 +0100" stop="20151124185000 +0100" originid="" reserve="no">
    <date>2015-11-26</date>
    <title>Anger Management</title>
    <subTitle>Charlie et la petite curieuse</subTitle>
    <desc>Charlie devient paranoïaque lorsqu'il découvre, avec surprise, qu'il sort avec une détective privée. Lacey rejoint Nolan et emménage dans sa... (Lire la suite).(n)</desc>
  </programme>
  <programme channel="test" start="20151124185000 +0100" stop="20151124191000 +0100" originid="" reserve="no">
    <date>2015-11-26</date>
    <title>Anger Management</title>
    <subTitle>Soeurs ennemies</subTitle>
    <desc>Charlie tombe tête baissée dans le piège astucieusement tendu par Jordan. Celui-ci l'autorise à lui arranger un rendez-vous avec une fille, sa... (Lire la suite).(n)</desc>
  </programme>
  <programme channel="test" start="20151124191000 +0100" stop="20151124193000 +0100" originid="" reserve="no">
    <date>2015-11-26</date>
    <title>Parks and Recreation</title>
    <subTitle>Jumelage</subTitle>
    <desc>Leslie accueille une délégation venue tout droit de la ville jumelée à Pawnee au Venezuela, Boraqua. Immédiatement, certaines différences... (Lire la suite).(n)</desc>
  </programme>
  <programme channel="test" start="20151124193000 +0100" stop="20151124195500 +0100" originid="" reserve="no">
    <date>2015-11-26</date>
    <title>Parks and Recreation</title>
    <subTitle>Parc Express</subTitle>
    <desc>Leslie et quelques autres volontaires du comité apportent leur aide à une organisation locale qui souhaite construire une petite aire de jeux,... (Lire la suite).(n)</desc>
  </programme>
  <programme channel="test" start="20151124195500 +0100" stop="20151124200500 +0100" originid="" reserve="no">
    <date>2015-11-26</date>
    <title>Workingirls</title>
    <subTitle>La visite médicale</subTitle>
    <desc>Le jour de la visite médicale, les deux Sophie se font un plaisir de prévenir Hélène que le médecin est un homme, ce qui fait paniquer leur... (Lire la suite).(n)</desc>
  </programme>
  <programme channel="test" start="20151124200500 +0100" stop="20151124205000 +0100" originid="" reserve="no">
    <date>2015-11-26</date>
    <title>Le tube</title>
    <subTitle />
    <desc>Web, télévision, radio, print : avec sérieux et bonne humeur, Ophélie Meunier évoque celles et ceux qui transforment le monde des médias,... (Lire la suite).(n)</desc>
  </programme>
  <programme channel="test" start="20151124205000 +0100" stop="20151124213500 +0100" originid="" reserve="no">
    <date>2015-11-26</date>
    <title>Fear The Walking Dead</title>
    <subTitle>Retrouvailles</subTitle>
    <desc>Les émeutes dévastent le centre-ville : Travis, Chris et Liza, accompagnés de la famille Salazar, tentent de trouver un endroit sûr pour échapper... (Lire la suite).(n)</desc>
  </programme>
  <programme channel="test" start="20151124213500 +0100" stop="20151124222000 +0100" originid="" reserve="no">
    <date>2015-11-26</date>
    <title>Fear The Walking Dead</title>
    <subTitle>Quarantaine</subTitle>
    <desc>Madison et Travis voient arriver la Garde Nationale dans leur quartier alors que l'atmosphère devient de plus en plus anxiogène avec l'infection... (Lire la suite).(n)</desc>
  </programme>
  <programme channel="test" start="20151124222000 +0100" stop="20151124231000 +0100" originid="" reserve="no">
    <date>2015-11-26</date>
    <title>Homeland</title>
    <subTitle />
    <desc>Carrie, qui ne travaille plus pour la CIA, est installée en Allemagne avec sa fille. Elle occupe désormais le poste de conseillère pour la... (Lire la suite).(n)</desc>
  </programme>
  <programme channel="test" start="20151124231000 +0100" stop="20151124235500 +0100" originid="" reserve="no">
    <date>2015-11-26</date>
    <title>Fear The Walking Dead</title>
    <subTitle>Retrouvailles</subTitle>
    <desc>Les émeutes dévastent le centre-ville : Travis, Chris et Liza, accompagnés de la famille Salazar, tentent de trouver un endroit sûr pour échapper... (Lire la suite).(n)</desc>
  </programme>
  <programme channel="test" start="20151124235500 +0100" stop="20151125004000 +0100" originid="" reserve="no">
    <date>2015-11-26</date>
    <title>Fear The Walking Dead</title>
    <subTitle>Quarantaine</subTitle>
    <desc>Madison et Travis voient arriver la Garde Nationale dans leur quartier alors que l'atmosphère devient de plus en plus anxiogène avec l'infection... (Lire la suite).(n)</desc>
  </programme>
</tv>