<?xml version="1.0" encoding="utf-8"?>
<tv xmlns:xsi="http://www.w3.org/2001/XMLSchema-instance" xmlns:xsd="http://www.w3.org/2001/XMLSchema">
  <programme channel="test" start="20151124064000 +0100" stop="20151124073000 +0100" originid="" reserve="no">
    <date>2015-11-26</date>
    <title>Les grandes aventurières</title>
    <subTitle>Gertrude Bell, exploratrice du désert</subTitle>
    <desc>Les exploits de Gertrude Bell, une Anglaise qui, pendant la Première Guerre mondiale, risqua sa vie pour récolter des informations indispensables... (Lire la suite).(n)</desc>
  </programme>
  <programme channel="test" start="20151124073000 +0100" stop="20151124082000 +0100" originid="" reserve="no">
    <date>2015-11-26</date>
    <title>Les grandes aventurières</title>
    <subTitle>Marguerite Harrison, une espionne à Moscou</subTitle>
    <desc>La vie de Marguerite Harrison, jeune Américaine de la Côte est, bascule en 1915, lorsque son mari meurt d'une tumeur au cerveau. Contrainte de... (Lire la suite).(n)</desc>
  </programme>
  <programme channel="test" start="20151124082000 +0100" stop="20151124091000 +0100" originid="" reserve="no">
    <date>2015-11-26</date>
    <title>Alice, une princesse pas comme les autres</title>
    <subTitle />
    <desc>L'histoire de la princesse Alice de Battenberg, petite-fille de la Reine Victoria et mère du prince Philip, l'époux de la Reine d'Angleterre, est... (Lire la suite).(n)</desc>
  </programme>
  <programme channel="test" start="20151124091000 +0100" stop="20151124102500 +0100" originid="" reserve="no">
    <date>2015-11-26</date>
    <title>Philby, l'espion qui fit trembler l'Angleterre</title>
    <subTitle />
    <desc>Haut placé dans les années 1940 et 1950 dans la section contre-espionnage des services secrets britanniques, Kim Philby est devenu la figure... (Lire la suite).(n)</desc>
  </programme>
  <programme channel="test" start="20151124102500 +0100" stop="20151124111500 +0100" originid="" reserve="no">
    <date>2015-11-26</date>
    <title>Les Roméo de la Stasi</title>
    <subTitle />
    <desc>Pendant la guerre froide, des agents est-allemands ont été chargés de séduire des secrétaires de l'Ouest pour récolter des renseignements... (Lire la suite).(n)</desc>
  </programme>
  <programme channel="test" start="20151124111500 +0100" stop="20151124112000 +0100" originid="" reserve="no">
    <date>2015-11-26</date>
    <title>Brèves d'histoire</title>
    <subTitle>Voltaire bon à rouer</subTitle>
    <desc>L'historien de l'insolite Jean-Paul Rouland évoque toutes les petites histoires cocasses et les anecdotes qui ont fait la grande... (Lire la suite).(n)</desc>
  </programme>
  <programme channel="test" start="20151124112000 +0100" stop="20151124131000 +0100" originid="" reserve="no">
    <date>2015-11-26</date>
    <title>La mort de Marie-Antoinette</title>
    <subTitle />
    <desc>Lorsqu'elle épouse Louis XVI, la jeune Marie-Antoinette quitte son Autriche natale pour s'établir en France. Après des années de bonheur facile,... (Lire la suite).(n)</desc>
  </programme>
  <programme channel="test" start="20151124131000 +0100" stop="20151124135000 +0100" originid="" reserve="no">
    <date>2015-11-26</date>
    <title>Historiquement show</title>
    <subTitle>Seconde Guerre mondiale</subTitle>
    <desc>Une émission sur les faits historiques animée par Jean-Christophe Buisson, qui reçoit Olivier Wieviorka pour le livre qu'il a dirigé avec Jean... (Lire la suite).(n)</desc>
  </programme>
  <programme channel="test" start="20151124135000 +0100" stop="20151124142000 +0100" originid="" reserve="no">
    <date>2015-11-26</date>
    <title>Les grands assassinats de l'histoire</title>
    <subTitle>Le roi Alexandre Ier de Yougoslavie</subTitle>
    <desc>En 1934, le roi Alexandre Ier de Yougoslavie, en visite dans le port de Marseille, est assassiné, à la grande surprise des autorités... (Lire la suite).(n)</desc>
  </programme>
  <programme channel="test" start="20151124142000 +0100" stop="20151124144500 +0100" originid="" reserve="no">
    <date>2015-11-26</date>
    <title>Les grands assassinats de l'histoire</title>
    <subTitle>Le tsar Nicolas II</subTitle>
    <desc>En 1918, à Ekaterinbourg, le tsar Nicolas II et sa famille sont exécutés par les révolutionnaires qui ont pris de le pouvoir dans l'empire... (Lire la suite).(n)</desc>
  </programme>
  <programme channel="test" start="20151124144500 +0100" stop="20151124155000 +0100" originid="" reserve="no">
    <date>2015-11-26</date>
    <title>1913 : sur les rails de l'Europe</title>
    <subTitle>De Londres à Monte-Carlo</subTitle>
    <desc>En utilisant un guide de voyage publié en 1913, Michael Portillo traverse l'Europe en train, s'arrêtant dans les villes et villages décrits dans... (Lire la suite).(n)</desc>
  </programme>
  <programme channel="test" start="20151124155000 +0100" stop="20151124165000 +0100" originid="" reserve="no">
    <date>2015-11-26</date>
    <title>Rococo</title>
    <subTitle />
    <desc>Goya a sondé la noirceur des âmes avec exubérance, Longhi a observé la décadence vénitienne, Messerschmidt, trouvé sa place parmi les sculpteurs... (Lire la suite).(n)</desc>
  </programme>
  <programme channel="test" start="20151124165000 +0100" stop="20151124170000 +0100" originid="" reserve="no">
    <date>2015-11-26</date>
    <title>Masterworks</title>
    <subTitle>The Picture Gallery in Berlin (n°2)</subTitle>
    <desc>Une visite guidée qui fait la part belles aux oeuvres d'arts exposées à Berlin, une place d'art réputée dans le monde entier pour ses... (Lire la suite).(n)</desc>
  </programme>
  <programme channel="test" start="20151124170000 +0100" stop="20151124175000 +0100" originid="" reserve="no">
    <date>2015-11-26</date>
    <title>René Girard, la violence et le sacré</title>
    <subTitle />
    <desc>En 2006, le philosophe René Girard revenait, avec Pierre-André Boutang et Benoît Chantre, sur les grandes étapes de sa carrière... (Lire la suite).(n)</desc>
  </programme>
  <programme channel="test" start="20151124175000 +0100" stop="20151124183500 +0100" originid="" reserve="no">
    <date>2015-11-26</date>
    <title>La vie privée des pharaons</title>
    <subTitle>Les secrets du lotus bleu</subTitle>
    <desc>Dans l'Egypte antique, les sépultures des nobles étaient couvertes de fresques peintes. Parmi les motifs les plus courants se trouve celui du... (Lire la suite).(n)</desc>
  </programme>
  <programme channel="test" start="20151124183500 +0100" stop="20151124184000 +0100" originid="" reserve="no">
    <date>2015-11-26</date>
    <title>Brèves d'histoire</title>
    <subTitle>L'hérédité d'Alembert</subTitle>
    <desc>L'historien de l'insolite Jean-Paul Rouland évoque toutes les petites histoires cocasses et les anecdotes qui ont fait la grande... (Lire la suite).(n)</desc>
  </programme>
  <programme channel="test" start="20151124184000 +0100" stop="20151124184500 +0100" originid="" reserve="no">
    <date>2015-11-26</date>
    <title>Brèves d'histoire</title>
    <subTitle>Zoé dernière favorite</subTitle>
    <desc>L'historien de l'insolite Jean-Paul Rouland évoque toutes les petites histoires cocasses et les anecdotes qui ont fait la grande... (Lire la suite).(n)</desc>
  </programme>
  <programme channel="test" start="20151124184500 +0100" stop="20151124194000 +0100" originid="" reserve="no">
    <date>2015-11-26</date>
    <title>Du D-Day à Diên Biên Phu</title>
    <subTitle />
    <desc>Le parcours édifiant des prisonniers allemands capturés après le Débarquement, qui se sont engagés ensuite dans la Légion et ont combattu en... (Lire la suite).(n)</desc>
  </programme>
  <programme channel="test" start="20151124194000 +0100" stop="20151124195000 +0100" originid="" reserve="no">
    <date>2015-11-26</date>
    <title>Histoire de comprendre</title>
    <subTitle>Reykjavik 1986, la fin de la guerre froide</subTitle>
    <desc>Contre toute attente, le sommet de Reykjavik, en 1986, a permis de mettre un terme à la guerre froide à laquelle se livraient les blocs américain... (Lire la suite).(n)</desc>
  </programme>
  <programme channel="test" start="20151124195000 +0100" stop="20151124200500 +0100" originid="" reserve="no">
    <date>2015-11-26</date>
    <title>Histoire de comprendre</title>
    <subTitle>1962, pourquoi la crise de Cuba</subTitle>
    <desc>En 1962, des avions américains repèrent des rampes de lancement soviétiques sur le territoire cubain : la tension entre les USA et l'URSS est à... (Lire la suite).(n)</desc>
  </programme>
  <programme channel="test" start="20151124200500 +0100" stop="20151124203000 +0100" originid="" reserve="no">
    <date>2015-11-26</date>
    <title>Les grands assassinats de l'histoire</title>
    <subTitle>L'archiduc François-Ferdinand</subTitle>
    <desc>Le 28 juin 1914, l'assassinat de l'archiduc François-Ferdinand, héritier du trône austro-hongrois, a précipité le déclenchement de la Première... (Lire la suite).(n)</desc>
  </programme>
  <programme channel="test" start="20151124203000 +0100" stop="20151124204000 +0100" originid="" reserve="no">
    <date>2015-11-26</date>
    <title>Brèves d'histoire</title>
    <subTitle>La rue Chanoinesse</subTitle>
    <desc>L'historien de l'insolite Jean-Paul Rouland évoque toutes les petites histoires cocasses et les anecdotes qui ont fait la grande... (Lire la suite).(n)</desc>
  </programme>
  <programme channel="test" start="20151124204000 +0100" stop="20151124212500 +0100" originid="" reserve="no">
    <date>2015-11-26</date>
    <title>Léonard de Vinci : la fresque disparue</title>
    <subTitle />
    <desc>En 1504, Léonard de Vinci entreprend l'un des travaux les plus ambitieux de sa carrière : la fresque de la Bataille d'Anghiari au Palazzo... (Lire la suite).(n)</desc>
  </programme>
  <programme channel="test" start="20151124212500 +0100" stop="20151124221500 +0100" originid="" reserve="no">
    <date>2015-11-26</date>
    <title>Léonard de Vinci</title>
    <subTitle>Léonard de Vinci</subTitle>
    <desc>Il y a une dizaine d'années, Peter Silverman, un marchand d'art, repère un dessin d'un artiste allemand inconnu du XIXe siècle au cours d'une... (Lire la suite).(n)</desc>
  </programme>
  <programme channel="test" start="20151124221500 +0100" stop="20151124230000 +0100" originid="" reserve="no">
    <date>2015-11-26</date>
    <title>A la recherche de l'art perdu</title>
    <subTitle>Le vol de «La Joconde</subTitle>
    <desc>En 1911, «La Joconde» disparaît mystérieusement du Louvre : pendant deux ans, les théories les plus extravagantes circulent sur le sort du... (Lire la suite).(n)</desc>
  </programme>
  <programme channel="test" start="20151124230000 +0100" stop="20151124235500 +0100" originid="" reserve="no">
    <date>2015-11-26</date>
    <title>William Colby : Sur les traces de mon père, cet espion</title>
    <subTitle />
    <desc>Portrait de William Colby, légende des services secrets américains, depuis ses débuts comme officier OSS jusqu'à sa prise en main de la... (Lire la suite).(n)</desc>
  </programme>
  <programme channel="test" start="20151124235500 +0100" stop="20151125004500 +0100" originid="" reserve="no">
    <date>2015-11-26</date>
    <title>Radio Free Europe</title>
    <subTitle>La guerre des ondes</subTitle>
    <desc>C'est en 1950, à Munich, que les Américains fondent la station RFE - Radio Free Europe - pour émettre à destination des pays du bloc soviétique.... (Lire la suite).(n)</desc>
  </programme>
</tv>