<?xml version="1.0" encoding="utf-8"?>
<tv xmlns:xsi="http://www.w3.org/2001/XMLSchema-instance" xmlns:xsd="http://www.w3.org/2001/XMLSchema">
  <programme channel="test" start="20151124080000 +0100" stop="20151124110000 +0100" originid="" reserve="no">
    <date>2015-11-26</date>
    <title>OMtv</title>
    <subTitle />
    <desc>(Lire la suite).(n)</desc>
  </programme>
  <programme channel="test" start="20151124110000 +0100" stop="20151124140000 +0100" originid="" reserve="no">
    <date>2015-11-26</date>
    <title>OMtv</title>
    <subTitle />
    <desc>(Lire la suite).(n)</desc>
  </programme>
  <programme channel="test" start="20151124140000 +0100" stop="20151124170000 +0100" originid="" reserve="no">
    <date>2015-11-26</date>
    <title>OMtv</title>
    <subTitle />
    <desc>(Lire la suite).(n)</desc>
  </programme>
  <programme channel="test" start="20151124170000 +0100" stop="20151124180000 +0100" originid="" reserve="no">
    <date>2015-11-26</date>
    <title>OMtv</title>
    <subTitle />
    <desc>(Lire la suite).(n)</desc>
  </programme>
  <programme channel="test" start="20151124180000 +0100" stop="20151124181000 +0100" originid="" reserve="no">
    <date>2015-11-26</date>
    <title>Un jour à l'OM</title>
    <subTitle />
    <desc>(Lire la suite).(n)</desc>
  </programme>
  <programme channel="test" start="20151124181000 +0100" stop="20151124184000 +0100" originid="" reserve="no">
    <date>2015-11-26</date>
    <title>Objectif match</title>
    <subTitle />
    <desc>Saison 2015-2016, 14e journée (Lire la suite).(n)</desc>
  </programme>
  <programme channel="test" start="20151124184000 +0100" stop="20151124190000 +0100" originid="" reserve="no">
    <date>2015-11-26</date>
    <title>Football (Hyères / Marseille)</title>
    <subTitle />
    <desc>(Lire la suite).(n)</desc>
  </programme>
  <programme channel="test" start="20151124190000 +0100" stop="20151124191000 +0100" originid="" reserve="no">
    <date>2015-11-26</date>
    <title>Un jour à l'OM</title>
    <subTitle />
    <desc>(Lire la suite).(n)</desc>
  </programme>
  <programme channel="test" start="20151124191000 +0100" stop="20151124194000 +0100" originid="" reserve="no">
    <date>2015-11-26</date>
    <title>Objectif match</title>
    <subTitle />
    <desc>Saison 2015-2016, 14e journée (Lire la suite).(n)</desc>
  </programme>
  <programme channel="test" start="20151124194000 +0100" stop="20151124200000 +0100" originid="" reserve="no">
    <date>2015-11-26</date>
    <title>Football (Hyères / Marseille)</title>
    <subTitle />
    <desc>(Lire la suite).(n)</desc>
  </programme>
  <programme channel="test" start="20151124200000 +0100" stop="20151124201000 +0100" originid="" reserve="no">
    <date>2015-11-26</date>
    <title>Un jour à l'OM</title>
    <subTitle />
    <desc>(Lire la suite).(n)</desc>
  </programme>
  <programme channel="test" start="20151124201000 +0100" stop="20151124204000 +0100" originid="" reserve="no">
    <date>2015-11-26</date>
    <title>Objectif match</title>
    <subTitle />
    <desc>Saison 2015-2016, 14e journée (Lire la suite).(n)</desc>
  </programme>
  <programme channel="test" start="20151124204000 +0100" stop="20151124210000 +0100" originid="" reserve="no">
    <date>2015-11-26</date>
    <title>Football (Hyères / Marseille)</title>
    <subTitle />
    <desc>(Lire la suite).(n)</desc>
  </programme>
  <programme channel="test" start="20151124210000 +0100" stop="20151124211000 +0100" originid="" reserve="no">
    <date>2015-11-26</date>
    <title>Un jour à l'OM</title>
    <subTitle />
    <desc>(Lire la suite).(n)</desc>
  </programme>
  <programme channel="test" start="20151124211000 +0100" stop="20151124214000 +0100" originid="" reserve="no">
    <date>2015-11-26</date>
    <title>Objectif match</title>
    <subTitle />
    <desc>Saison 2015-2016, 14e journée (Lire la suite).(n)</desc>
  </programme>
  <programme channel="test" start="20151124214000 +0100" stop="20151124220000 +0100" originid="" reserve="no">
    <date>2015-11-26</date>
    <title>Football (Hyères / Marseille)</title>
    <subTitle />
    <desc>(Lire la suite).(n)</desc>
  </programme>
  <programme channel="test" start="20151124220000 +0100" stop="20151124221000 +0100" originid="" reserve="no">
    <date>2015-11-26</date>
    <title>Un jour à l'OM</title>
    <subTitle />
    <desc>(Lire la suite).(n)</desc>
  </programme>
  <programme channel="test" start="20151124221000 +0100" stop="20151124224000 +0100" originid="" reserve="no">
    <date>2015-11-26</date>
    <title>Objectif match</title>
    <subTitle />
    <desc>Saison 2015-2016, 14e journée (Lire la suite).(n)</desc>
  </programme>
  <programme channel="test" start="20151124224000 +0100" stop="20151124230000 +0100" originid="" reserve="no">
    <date>2015-11-26</date>
    <title>Football (Hyères / Marseille)</title>
    <subTitle />
    <desc>(Lire la suite).(n)</desc>
  </programme>
  <programme channel="test" start="20151124230000 +0100" stop="20151124231000 +0100" originid="" reserve="no">
    <date>2015-11-26</date>
    <title>Un jour à l'OM</title>
    <subTitle />
    <desc>(Lire la suite).(n)</desc>
  </programme>
  <programme channel="test" start="20151124231000 +0100" stop="20151124234000 +0100" originid="" reserve="no">
    <date>2015-11-26</date>
    <title>Objectif match</title>
    <subTitle />
    <desc>Saison 2015-2016, 14e journée (Lire la suite).(n)</desc>
  </programme>
  <programme channel="test" start="20151124234000 +0100" stop="20151125000000 +0100" originid="" reserve="no">
    <date>2015-11-26</date>
    <title>Football (Hyères / Marseille)</title>
    <subTitle />
    <desc>(Lire la suite).(n)</desc>
  </programme>
</tv>